jet_bridge/__init__.py
jet_bridge/__main__.py
jet_bridge/app.py
jet_bridge/configuration.py
jet_bridge/jet_bridge_store.sqlite3
jet_bridge/media.py
jet_bridge/router.py
jet_bridge/settings.py
jet_bridge/__pycache__/__init__.cpython-313.pyc
jet_bridge/__pycache__/__init__.cpython-36.pyc
jet_bridge/__pycache__/app.cpython-36.pyc
jet_bridge/__pycache__/configuration.cpython-36.pyc
jet_bridge/__pycache__/media.cpython-36.pyc
jet_bridge/__pycache__/router.cpython-36.pyc
jet_bridge/__pycache__/settings.cpython-36.pyc
jet_bridge/commands/__init__.py
jet_bridge/handlers/__init__.py
jet_bridge/handlers/not_found.py
jet_bridge/handlers/temporary_redirect.py
jet_bridge/handlers/view.py
jet_bridge/handlers/__pycache__/__init__.cpython-36.pyc
jet_bridge/handlers/__pycache__/not_found.cpython-36.pyc
jet_bridge/handlers/__pycache__/temporary_redirect.cpython-36.pyc
jet_bridge/handlers/__pycache__/view.cpython-36.pyc
jet_bridge/metadata/postgresql_jet-database-dev.jetadmin.io_9660_db-new-app-29-pr_5d9f37e01cdcb1e2f34ba8b55c2539f422fad3a6a5301af6f8d41c5eb77d06ca_cf40fbc2.dump
jet_bridge/metadata/postgresql_jet-database-dev.jetadmin.io_9660_db-test-2150-pro_f64fe59e72194d8095bbc488ce81938a166f4a216993bec3dfdeeec4c82cbf8e_7ed5958c.dump
jet_bridge/metadata/postgresql_testdb-dev.jetadmin.io_9680_demo_35abfc8c8260e0ad78661434ef41845f241d6f495f8db9439f92628beb857b37_52957740.dump
jet_bridge/metadata/postgresql_testdb-dev.jetadmin.io_9680_postgres_13682ed4cd6e80b58575a6e7a3428df3603bebf878b7e51ea414ec4f9b48f0a0_7ed5958c.dump
jet_bridge/tasks/__init__.py
jet_bridge/tasks/release_inactive_graphql_schemas.py
jet_bridge/tasks/__pycache__/__init__.cpython-36.pyc
jet_bridge/tasks/__pycache__/release_inactive_graphql_schemas.cpython-36.pyc
jet_bridge/utils/__init__.py
jet_bridge/utils/async_exec.py
jet_bridge/utils/create_config.py
jet_bridge/utils/settings.py
jet_bridge/utils/__pycache__/__init__.cpython-36.pyc
jet_bridge/utils/__pycache__/async_exec.cpython-36.pyc
jet_bridge-1.12.7.dist-info/LICENSE
jet_bridge-1.12.7.dist-info/METADATA
jet_bridge-1.12.7.dist-info/WHEEL
jet_bridge-1.12.7.dist-info/entry_points.txt
jet_bridge-1.12.7.dist-info/top_level.txt
jet_bridge-1.12.7.dist-info/RECORD
