Metadata-Version: 2.1
Name: jet-bridge
Version: 1.12.7
Summary: UNKNOWN
Home-page: https://github.com/jet-admin/jet-bridge
Author: Denis Kildishev
Author-email: support@jetadmin.io
License: MIT
Platform: UNKNOWN
Requires-Dist: tornado (==5.1.1)
Requires-Dist: six
Requires-Dist: jet-bridge-base (==1.12.7)
Requires-Dist: paramiko (==2.8.1)
Requires-Dist: sshtunnel
